LICENSE
README.rst
pyproject.toml
setup.py
serpyco/__init__.py
serpyco/decorator.py
serpyco/encoder.c
serpyco/exception.py
serpyco/field.py
serpyco/mixin.py
serpyco/schema.py
serpyco/serializer.c
serpyco/util.py
serpyco/validator.py
serpycow.egg-info/PKG-INFO
serpycow.egg-info/SOURCES.txt
serpycow.egg-info/dependency_links.txt
serpycow.egg-info/requires.txt
serpycow.egg-info/top_level.txt
tests/test_benchmarks.py
tests/test_unit.py