Metadata-Version: 2.1
Name: serpycow
Version: 1.3.0
Summary: Fast serialization of dataclasses using Cython
Author-email: Sébastien Grignard <pub@amakaze.org>, Patrick Mazulo <mazulo@d7.dev>
License: MIT
Project-URL: Homepage, https://github.com/7ws/serpyco
Project-URL: Bug Tracker, https://github.com/7ws/serpyco/issues
Classifier: Development Status :: 5 - Production/Stable
Classifier: Intended Audience :: Developers
Classifier: License :: OSI Approved :: MIT License
Classifier: Programming Language :: Python :: 3
Classifier: Topic :: Software Development :: Libraries
Classifier: Operating System :: OS Independent
Classifier: Programming Language :: Python :: 3
Classifier: Programming Language :: Python :: 3.7
Classifier: Programming Language :: Python :: 3.8
Classifier: Programming Language :: Python :: 3.9
Classifier: Programming Language :: Python :: 3.10
Requires-Python: >=3.7
Provides-Extra: dev
Provides-Extra: build-doc
License-File: LICENSE
